twitter_dl/__init__.py
twitter_dl/__main__.py
twitter_dl/downloader.py
twitter_dl/exceptions.py
twitter_dl/threaded_aio_dlder.py
twitter_dl/unittest.py
twitter_dl-0.2.0.dist-info/LICENSE
twitter_dl-0.2.0.dist-info/METADATA
twitter_dl-0.2.0.dist-info/WHEEL
twitter_dl-0.2.0.dist-info/entry_points.txt
twitter_dl-0.2.0.dist-info/top_level.txt
twitter_dl-0.2.0.dist-info/RECORD
