Metadata-Version: 2.1
Name: twitter-dl
Version: 0.2.0
Summary: Download tweet images and videos
Home-page: https://github.com/stockbsd/twitter-media-dl
Author: stockbsd
Author-email: stockbsd@gmail.com
License: UNKNOWN
Project-URL: Bug Reports, https://github.com/stockbsd/twitter-media-dl
Project-URL: Source, https://github.com/stockbsd/twitter-media-dl
Keywords: twitter,asyncio,media
Platform: UNKNOWN
Classifier: Programming Language :: Python :: 3
Classifier: License :: OSI Approved :: MIT License
Classifier: Operating System :: OS Independent
Requires-Python: >=3.6
Requires-Dist: requests (>=2.20.0)
Requires-Dist: aiohttp (>=3.4.4)
